{
    "templateName": "left-right-bottom",
    "holders": {
        "topleft": {
            "widgets": [
                {
                    "templateName": "hello"
                },
                {
                    "templateName": "bye"
                },
                {
                    "templateName": "hello"
                }
            ]
        },
        "topright": {
            "widgets": [
                {
                    "templateName": "hello"
                },
                {
                    "templateName": "bye"
                },
                {
                    "templateName": "hello"
                }
            ]
        },
        "bottom": {
            "widgets": [
                {
                    "templateName": "hello"
                },
                {
                    "templateName": "bye"
                },
                {
                    "templateName": "hello"
                }
            ]
        }
    }
}