{
  "1-col": {
    "description": "Description of template \"1-col\"",
    "holders" : [
      "column"
    ]
  },
  "2-cols": {
    "description": "Description of template \"2-cols\"",
    "holders" : [
      "column",
      "left",
      "right"
    ]
  },
  "2x2": {
    "description": "Description of template \"2x2\"",
    "holders" : [
      "column",
      "topleft",
      "topright",
      "bottomleft",
      "bottomright"
    ]
  },
  "left-right-bottom": {
    "description": "Description of template \"left-right-bottom\"",
    "holders" : [
      "column",
      "topleft",
      "topright",
      "bottom"
    ]
  }
}
